mozilla_schema_generator/__init__.py
mozilla_schema_generator/__main__.py
mozilla_schema_generator/bhr_ping.py
mozilla_schema_generator/common_ping.py
mozilla_schema_generator/config.py
mozilla_schema_generator/generic_ping.py
mozilla_schema_generator/glean_ping.py
mozilla_schema_generator/main_ping.py
mozilla_schema_generator/matcher.py
mozilla_schema_generator/probes.py
mozilla_schema_generator/schema.py
mozilla_schema_generator/utils.py
mozilla_schema_generator/validate_bigquery.py
mozilla_schema_generator/configs/deletion_request.yaml
mozilla_schema_generator/configs/glean.yaml
mozilla_schema_generator/configs/main.yaml
mozilla_schema_generator/configs/new_profile.yaml
mozilla_schema_generator/configs/sync.yaml
mozilla_schema_generator-0.5.1.dist-info/AUTHORS.rst
mozilla_schema_generator-0.5.1.dist-info/LICENSE
mozilla_schema_generator-0.5.1.dist-info/METADATA
mozilla_schema_generator-0.5.1.dist-info/WHEEL
mozilla_schema_generator-0.5.1.dist-info/entry_points.txt
mozilla_schema_generator-0.5.1.dist-info/top_level.txt
mozilla_schema_generator-0.5.1.dist-info/RECORD
