Metadata-Version: 2.1
Name: mozilla-schema-generator
Version: 0.5.1
Summary: Create full representations of schemas using the probe info service.
Home-page: https://github.com/mozilla/mozilla-schema-generator
Author: Mozilla Corporation
Author-email: fx-data-dev@mozilla.org
License: MIT
Keywords: mozilla-schema-generator
Platform: UNKNOWN
Classifier: Intended Audience :: Developers
Classifier: Programming Language :: Python :: 3
Classifier: Programming Language :: Python :: 3.7
Requires-Python: >=3.6.0
Requires-Dist: click
Requires-Dist: jsonschema
Requires-Dist: pyyaml
Requires-Dist: requests
Requires-Dist: gitpython
